torchunlearn/__init__.py
torchunlearn/setup.py
torchunlearn/attacks/__init__.py
torchunlearn/attacks/attack.py
torchunlearn/attacks/attacks/__init__.py
torchunlearn/attacks/attacks/_differential_evolution.py
torchunlearn/attacks/attacks/apgd.py
torchunlearn/attacks/attacks/apgdt.py
torchunlearn/attacks/attacks/autoattack.py
torchunlearn/attacks/attacks/bim.py
torchunlearn/attacks/attacks/cw.py
torchunlearn/attacks/attacks/deepfool.py
torchunlearn/attacks/attacks/difgsm.py
torchunlearn/attacks/attacks/eaden.py
torchunlearn/attacks/attacks/eadl1.py
torchunlearn/attacks/attacks/eotpgd.py
torchunlearn/attacks/attacks/fab.py
torchunlearn/attacks/attacks/ffgsm.py
torchunlearn/attacks/attacks/fgsm.py
torchunlearn/attacks/attacks/gn.py
torchunlearn/attacks/attacks/jitter.py
torchunlearn/attacks/attacks/jsma.py
torchunlearn/attacks/attacks/mifgsm.py
torchunlearn/attacks/attacks/nifgsm.py
torchunlearn/attacks/attacks/onepixel.py
torchunlearn/attacks/attacks/pgd.py
torchunlearn/attacks/attacks/pgdl2.py
torchunlearn/attacks/attacks/pgdrs.py
torchunlearn/attacks/attacks/pgdrsl2.py
torchunlearn/attacks/attacks/pifgsm.py
torchunlearn/attacks/attacks/pifgsmpp.py
torchunlearn/attacks/attacks/pixle.py
torchunlearn/attacks/attacks/rfgsm.py
torchunlearn/attacks/attacks/sinifgsm.py
torchunlearn/attacks/attacks/sparsefool.py
torchunlearn/attacks/attacks/spsa.py
torchunlearn/attacks/attacks/square.py
torchunlearn/attacks/attacks/tifgsm.py
torchunlearn/attacks/attacks/tpgd.py
torchunlearn/attacks/attacks/upgd.py
torchunlearn/attacks/attacks/vanila.py
torchunlearn/attacks/attacks/vmifgsm.py
torchunlearn/attacks/attacks/vnifgsm.py
torchunlearn/attacks/wrappers/__init__.py
torchunlearn/attacks/wrappers/lgv.py
torchunlearn/attacks/wrappers/multiattack.py
torchunlearn/nn/__init__.py
torchunlearn/nn/robmodel.py
torchunlearn/nn/modules/__init__.py
torchunlearn/nn/modules/identity.py
torchunlearn/nn/modules/normalize.py
torchunlearn/optim/__init__.py
torchunlearn/optim/minimizer.py
torchunlearn-0.1.0.dist-info/METADATA
torchunlearn-0.1.0.dist-info/WHEEL
torchunlearn-0.1.0.dist-info/top_level.txt
torchunlearn-0.1.0.dist-info/RECORD
